twitterstats/__init__.py
twitterstats/api_client.py
TwitterStats-0.0.6.dist-info/AUTHORS
TwitterStats-0.0.6.dist-info/LICENCE
TwitterStats-0.0.6.dist-info/METADATA
TwitterStats-0.0.6.dist-info/WHEEL
TwitterStats-0.0.6.dist-info/top_level.txt
TwitterStats-0.0.6.dist-info/RECORD
