Metadata-Version: 2.1
Name: TwitterStats
Version: 0.0.6
Summary: Python Package to collect stats from Twitter API
Home-page: https://bas.codes
Author: Bas Steins
Author-email: blog@bascodes.com
License: MIT
Project-URL: Bug Tracker, https://bas.codes
Platform: UNKNOWN
Classifier: License :: OSI Approved :: MIT License
Classifier: Programming Language :: Python :: 3
Classifier: Programming Language :: Python :: 3.7
Requires-Python: >=3.6
License-File: LICENCE
License-File: AUTHORS
Requires-Dist: setuptools (>=42)
Requires-Dist: wheel
Requires-Dist: TwitterAPI (>=2.7.11)
